{"name":"TwoNet-Dev","className":"DataModel","filePaths":["dev.project.json"],"children":[{"name":"ReplicatedStorage","className":"ReplicatedStorage","children":[{"name":"Packages","className":"Folder","children":[{"name":"FastSig","className":"ModuleScript","filePaths":["Packages\\FastSig.lua"]},{"name":"FastTasks","className":"ModuleScript","filePaths":["Packages\\FastTasks.lua"]},{"name":"_Index","className":"Folder","children":[{"name":"twocelgames_fastsig@0.1.0","className":"Folder","children":[{"name":"FastTasks","className":"ModuleScript","filePaths":["Packages\\_Index\\twocelgames_fastsig@0.1.0\\FastTasks.lua"]},{"name":"fastsig","className":"ModuleScript","filePaths":["Packages\\_Index\\twocelgames_fastsig@0.1.0\\fastsig\\src\\init.luau","Packages\\_Index\\twocelgames_fastsig@0.1.0\\fastsig\\default.project.json"],"children":[{"name":"config","className":"ModuleScript","filePaths":["Packages\\_Index\\twocelgames_fastsig@0.1.0\\fastsig\\src\\config.luau"]},{"name":"types","className":"ModuleScript","filePaths":["Packages\\_Index\\twocelgames_fastsig@0.1.0\\fastsig\\src\\types.luau"]}]}]},{"name":"twocelgames_fasttasks@0.3.2","className":"Folder","children":[{"name":"fasttasks","className":"ModuleScript","filePaths":["Packages\\_Index\\twocelgames_fasttasks@0.3.2\\fasttasks\\src\\init.lua","Packages\\_Index\\twocelgames_fasttasks@0.3.2\\fasttasks\\default.project.json"],"children":[{"name":"config","className":"ModuleScript","filePaths":["Packages\\_Index\\twocelgames_fasttasks@0.3.2\\fasttasks\\src\\config.lua"]}]}]}]},{"name":"TwoNet","className":"ModuleScript","filePaths":["src\\init.luau"]}]}]}]}